{
  "id": "rss-20260426-004",
  "title": "South Korea police arrest man for posting AI photo of runaway wolf",
  "source": "rss:Hacker News Best (AI)",
  "source_url": "https://www.bbc.com/news/articles/c4gx1n0dl9no",
  "author": "Hacker News Best (AI)",
  "published_at": "2026-04-26T09:09:24.177403+00:00",
  "collected_at": "2026-04-26T09:09:24.177403+00:00",
  "summary": "韩国警方逮捕了一名男子，该男子因在社交媒体上发布 AI 生成的狼逃跑照片而涉嫌违法。此事件反映了 AI 图像生成技术在恶意使用方面带来的法律和伦理挑战，以及各国对 AI 生成内容监管的重视程度正在提升。",
  "score": 7,
  "tags": [
    "security",
    "vision"
  ],
  "audience": "intermediate",
  "status": "review",
  "updated_at": "2026-04-26T09:18:31.967729+00:00"
}